Workbook

Sheet 1. Operaciones
O1: NicaExport Trading, S.A.
O2: Operaciones
B4: ID_Operación | C4: Fecha | D4: Cliente | E4: Código Producto | F4: País Destino | G4: Unidades | H4: Precio FOB | I4: Costo Unitario | J4: Estado | K4: producto | L4: Categoria | M4: Región | N4: Arancel % | O4: Clasificación Mercado | P4: Valor FOB (Free On Board) | Q4: Costo total | R4: Utilidad | S4: Margen | T4: Nivel de rentabilidad | U4: Nivel de operación | V4: Prioridad comercial
B5: EX001 | C5: 46027 | D5: Comercial Maya | E5: P003 | F5: Guatemala | G5: 850 | H5: 4.8 | I5: 3.2 | J5: Embarcado | K5: =VLOOKUP(E:E,'2. Productos'!$C$3:$F$8,2,FALSE) -> Miel natural | L5: =VLOOKUP(E:E,'2. Productos'!$C$3:$E$8,3,FALSE) -> Apícola | M5: =VLOOKUP(F:F,'3. Mercados'!$C$3:$F$9,2,FALSE) -> Centroamérica | N5: =VLOOKUP(F:F,'3. Mercados'!$C$3:$F$9,3,FALSE) -> 0.03 | O5: =VLOOKUP(F:F,'3. Mercados'!$C$3:$F$9,4,FALSE) -> Estratégico | P5: =Tabla1[[#This Row],[Unidades]]*Tabla1[[#This Row],[Precio FOB]] -> 4080 | Q5: =Tabla1[[#This Row],[Unidades]]*Tabla1[[#This Row],[Costo Unitario]] -> 2720 | R5: =Tabla1[[#This Row],[Valor FOB (Free On Board)]]-Tabla1[[#This Row],[Costo total]] -> 1360 | S5: =Tabla1[[#This Row],[Utilidad]]/Tabla1[[#This Row],[Valor FOB (Free On Board)]] -> 0.33333333 | T5: =IF(Tabla1[[#This Row],[Margen]]>=30%,"Alta",IF(Tabla1[[#This Row],[Margen]]>=15%,"Media","Baja")) -> Alta | U5: =IF(Tabla1[[#This Row],[Valor FOB (Free On Board)]]>=10000,"Grande",IF(Tabla1[[#This Row],[Valor FOB (Free On Board)]]>=5000,"Mediana","Pequeña")) -> Pequeña | V5: =IF(AND(Tabla1[[#This Row],[Clasificación Mercado]]="Estratégico", Tabla1[[#This Row],[Margen]]>=0.3), "Alta", IF(AND(Tabla1[[#This Row],[Clasificación Mercado]]="Estratégico", Tabla1[[#This Row],[Margen]]<0.3), "Media", IF(AND(Tabla1[[#This Row],[Clasificación Mercado]]="Potencial", Tabla1[[#This Row],[Margen]]>=0.3), "Media", "Baja"))) -> Alta | AA5: Funciones condicionales
B6: EX002 | C6: 46034 | D6: Global Foods | E6: P001 | F6: EE.UU. | G6: 1200 | H6: 6.5 | I6: 4.1 | J6: Entregado | K6: =VLOOKUP(E:E,'2. Productos'!$C$3:$F$8,2,FALSE) -> Café especial | L6: =VLOOKUP(E:E,'2. Productos'!$C$3:$E$8,3,FALSE) -> Café | M6: =VLOOKUP(F:F,'3. Mercados'!$C$3:$F$9,2,FALSE) -> Norteamérica | N6: =VLOOKUP(F:F,'3. Mercados'!$C$3:$F$9,3,FALSE) -> 0.05 | O6: =VLOOKUP(F:F,'3. Mercados'!$C$3:$F$9,4,FALSE) -> Estratégico | P6: =Tabla1[[#This Row],[Unidades]]*Tabla1[[#This Row],[Precio FOB]] -> 7800 | Q6: =Tabla1[[#This Row],[Unidades]]*Tabla1[[#This Row],[Costo Unitario]] -> 4920 | R6: =Tabla1[[#This Row],[Valor FOB (Free On Board)]]-Tabla1[[#This Row],[Costo total]] -> 2880 | S6: =Tabla1[[#This Row],[Utilidad]]/Tabla1[[#This Row],[Valor FOB (Free On Board)]] -> 0.36923077 | T6: =IF(Tabla1[[#This Row],[Margen]]>=30%,"Alta",IF(Tabla1[[#This Row],[Margen]]>=15%,"Media","Baja")) -> Alta | U6: =IF(Tabla1[[#This Row],[Valor FOB (Free On Board)]]>=10000,"Grande",IF(Tabla1[[#This Row],[Valor FOB (Free On Board)]]>=5000,"Mediana","Pequeña")) -> Mediana | V6: =IF(AND(Tabla1[[#This Row],[Clasificación Mercado]]="Estratégico", Tabla1[[#This Row],[Margen]]>=0.3), "Alta", IF(AND(Tabla1[[#This Row],[Clasificación Mercado]]="Estratégico", Tabla1[[#This Row],[Margen]]<0.3), "Media", IF(AND(Tabla1[[#This Row],[Clasificación Mercado]]="Potencial", Tabla1[[#This Row],[Margen]]>=0.3), "Media", "Baja"))) -> Alta | Z6: ¿Cuántas operaciones se realizaron hacia Estados Unidos?
B7: EX003 | C7: 46042 | D7: Distribuidora Tica | E7: P004 | F7: Costa Rica | G7: 650 | H7: 8.2 | I7: 5.9 | J7: Embarcado | K7: =VLOOKUP(E:E,'2. Productos'!$C$3:$F$8,2,FALSE) -> Maní procesado | L7: =VLOOKUP(E:E,'2. Productos'!$C$3:$E$8,3,FALSE) -> Semillas | M7: =VLOOKUP(F:F,'3. Mercados'!$C$3:$F$9,2,FALSE) -> Centroamérica | N7: =VLOOKUP(F:F,'3. Mercados'!$C$3:$F$9,3,FALSE) -> 0.02 | O7: =VLOOKUP(F:F,'3. Mercados'!$C$3:$F$9,4,FALSE) -> Estratégico | P7: =Tabla1[[#This Row],[Unidades]]*Tabla1[[#This Row],[Precio FOB]] -> 5330 | Q7: =Tabla1[[#This Row],[Unidades]]*Tabla1[[#This Row],[Costo Unitario]] -> 3835 | R7: =Tabla1[[#This Row],[Valor FOB (Free On Board)]]-Tabla1[[#This Row],[Costo total]] -> 1495 | S7: =Tabla1[[#This Row],[Utilidad]]/Tabla1[[#This Row],[Valor FOB (Free On Board)]] -> 0.2804878 | T7: =IF(Tabla1[[#This Row],[Margen]]>=30%,"Alta",IF(Tabla1[[#This Row],[Margen]]>=15%,"Media","Baja")) -> Media | U7: =IF(Tabla1[[#This Row],[Valor FOB (Free On Board)]]>=10000,"Grande",IF(Tabla1[[#This Row],[Valor FOB (Free On Board)]]>=5000,"Mediana","Pequeña")) -> Mediana | V7: =IF(AND(Tabla1[[#This Row],[Clasificación Mercado]]="Estratégico", Tabla1[[#This Row],[Margen]]>=0.3), "Alta", IF(AND(Tabla1[[#This Row],[Clasificación Mercado]]="Estratégico", Tabla1[[#This Row],[Margen]]<0.3), "Media", IF(AND(Tabla1[[#This Row],[Clasificación Mercado]]="Potencial", Tabla1[[#This Row],[Margen]]>=0.3), "Media", "Baja"))) -> Media | Z7: =COUNTIF(Tabla1[País Destino],"EE.UU.") -> 20
B8: EX004 | C8: 46056 | D8: Iberia Foods | E8: P002 | F8: España | G8: 950 | H8: 7.1 | I8: 4.8 | J8: Pendiente | K8: =VLOOKUP(E:E,'2. Productos'!$C$3:$F$8,2,FALSE) -> Cacao en grano | L8: =VLOOKUP(E:E,'2. Productos'!$C$3:$E$8,3,FALSE) -> Cacao | M8: =VLOOKUP(F:F,'3. Mercados'!$C$3:$F$9,2,FALSE) -> Europa | N8: =VLOOKUP(F:F,'3. Mercados'!$C$3:$F$9,3,FALSE) -> 0.1 | O8: =VLOOKUP(F:F,'3. Mercados'!$C$3:$F$9,4,FALSE) -> Potencial | P8: =Tabla1[[#This Row],[Unidades]]*Tabla1[[#This Row],[Precio FOB]] -> 6745 | Q8: =Tabla1[[#This Row],[Unidades]]*Tabla1[[#This Row],[Costo Unitario]] -> 4560 | R8: =Tabla1[[#This Row],[Valor FOB (Free On Board)]]-Tabla1[[#This Row],[Costo total]] -> 2185 | S8: =Tabla1[[#This Row],[Utilidad]]/Tabla1[[#This Row],[Valor FOB (Free On Board)]] -> 0.32394366 | T8: =IF(Tabla1[[#This Row],[Margen]]>=30%,"Alta",IF(Tabla1[[#This Row],[Margen]]>=15%,"Media","Baja")) -> Alta | U8: =IF(Tabla1[[#This Row],[Valor FOB (Free On Board)]]>=10000,"Grande",IF(Tabla1[[#This Row],[Valor FOB (Free On Board)]]>=5000,"Mediana","Pequeña")) -> Mediana | V8: =IF(AND(Tabla1[[#This Row],[Clasificación Mercado]]="Estratégico", Tabla1[[#This Row],[Margen]]>=0.3), "Alta", IF(AND(Tabla1[[#This Row],[Clasificación Mercado]]="Estratégico", Tabla1[[#This Row],[Margen]]<0.3), "Media", IF(AND(Tabla1[[#This Row],[Clasificación Mercado]]="Potencial", Tabla1[[#This Row],[Margen]]>=0.3), "Media", "Baja"))) -> Media
B9: EX005 | C9: 46068 | D9: Comercial Azteca | E9: P005 | F9: México | G9: 500 | H9: 12.5 | I9: 8.7 | J9: Entregado | K9: =VLOOKUP(E:E,'2. Productos'!$C$3:$F$8,2,FALSE) -> Aceite de ajonjolí | L9: =VLOOKUP(E:E,'2. Productos'!$C$3:$E$8,3,FALSE) -> Aceites | M9: =VLOOKUP(F:F,'3. Mercados'!$C$3:$F$9,2,FALSE) -> Norteamérica | N9: =VLOOKUP(F:F,'3. Mercados'!$C$3:$F$9,3,FALSE) -> 0.08 | O9: =VLOOKUP(F:F,'3. Mercados'!$C$3:$F$9,4,FALSE) -> Potencial | P9: =Tabla1[[#This Row],[Unidades]]*Tabla1[[#This Row],[Precio FOB]] -> 6250 | Q9: =Tabla1[[#This Row],[Unidades]]*Tabla1[[#This Row],[Costo Unitario]] -> 4350 | R9: =Tabla1[[#This Row],[Valor FOB (Free On Board)]]-Tabla1[[#This Row],[Costo total]] -> 1900 | S9: =Tabla1[[#This Row],[Utilidad]]/Tabla1[[#This Row],[Valor FOB (Free On Board)]] -> 0.304 | T9: =IF(Tabla1[[#This Row],[Margen]]>=30%,"Alta",IF(Tabla1[[#This Row],[Margen]]>=15%,"Media","Baja")) -> Alta | U9: =IF(Tabla1[[#This Row],[Valor FOB (Free On Board)]]>=10000,"Grande",IF(Tabla1[[#This Row],[Valor FOB (Free On Board)]]>=5000,"Mediana","Pequeña")) -> Mediana | V9: =IF(AND(Tabla1[[#This Row],[Clasificación Mercado]]="Estratégico", Tabla1[[#This Row],[Margen]]>=0.3), "Alta", IF(AND(Tabla1[[#This Row],[Clasificación Mercado]]="Estratégico", Tabla1[[#This Row],[Margen]]<0.3), "Media", IF(AND(Tabla1[[#This Row],[Clasificación Mercado]]="Potencial", Tabla1[[#This Row],[Margen]]>=0.3), "Media", "Baja"))) -> Media | Z9: ¿Cuántas operaciones están pendientes?
B10: EX006 | C10: 46081 | D10: Global Foods | E10: P003 | F10: EE.UU. | G10: 1400 | H10: 4.8 | I10: 3.2 | J10: Entregado | K10: =VLOOKUP(E:E,'2. Productos'!$C$3:$F$8,2,FALSE) -> Miel natural | L10: =VLOOKUP(E:E,'2. Productos'!$C$3:$E$8,3,FALSE) -> Apícola | M10: =VLOOKUP(F:F,'3. Mercados'!$C$3:$F$9,2,FALSE) -> Norteamérica | N10: =VLOOKUP(F:F,'3. Mercados'!$C$3:$F$9,3,FALSE) -> 0.05 | O10: =VLOOKUP(F:F,'3. Mercados'!$C$3:$F$9,4,FALSE) -> Estratégico | P10: =Tabla1[[#This Row],[Unidades]]*Tabla1[[#This Row],[Precio FOB]] -> 6720 | Q10: =Tabla1[[#This Row],[Unidades]]*Tabla1[[#This Row],[Costo Unitario]] -> 4480 | R10: =Tabla1[[#This Row],[Valor FOB (Free On Board)]]-Tabla1[[#This Row],[Costo total]] -> 2240 | S10: =Tabla1[[#This Row],[Utilidad]]/Tabla1[[#This Row],[Valor FOB (Free On Board)]] -> 0.33333333 | T10: =IF(Tabla1[[#This Row],[Margen]]>=30%,"Alta",IF(Tabla1[[#This Row],[Margen]]>=15%,"Media","Baja")) -> Alta | U10: =IF(Tabla1[[#This Row],[Valor FOB (Free On Board)]]>=10000,"Grande",IF(Tabla1[[#This Row],[Valor FOB (Free On Board)]]>=5000,"Mediana","Pequeña")) -> Mediana | V10: =IF(AND(Tabla1[[#This Row],[Clasificación Mercado]]="Estratégico", Tabla1[[#This Row],[Margen]]>=0.3), "Alta", IF(AND(Tabla1[[#This Row],[Clasificación Mercado]]="Estratégico", Tabla1[[#This Row],[Margen]]<0.3), "Media", IF(AND(Tabla1[[#This Row],[Clasificación Mercado]]="Potencial", Tabla1[[#This Row],[Margen]]>=0.3), "Media", "Baja"))) -> Alta | Z10: =COUNTIF(Tabla1[Estado],"Pendiente") -> 15
B11: EX007 | C11: 46089 | D11: Distribuidora Tica | E11: P001 | F11: Costa Rica | G11: 900 | H11: 6.5 | I11: 4.1 | J11: Embarcado | K11: =VLOOKUP(E:E,'2. Productos'!$C$3:$F$8,2,FALSE) -> Café especial | L11: =VLOOKUP(E:E,'2. Productos'!$C$3:$E$8,3,FALSE) -> Café | M11: =VLOOKUP(F:F,'3. Mercados'!$C$3:$F$9,2,FALSE) -> Centroamérica | N11: =VLOOKUP(F:F,'3. Mercados'!$C$3:$F$9,3,FALSE) -> 0.02 | O11: =VLOOKUP(F:F,'3. Mercados'!$C$3:$F$9,4,FALSE) -> Estratégico | P11: =Tabla1[[#This Row],[Unidades]]*Tabla1[[#This Row],[Precio FOB]] -> 5850 | Q11: =Tabla1[[#This Row],[Unidades]]*Tabla1[[#This Row],[Costo Unitario]] -> 3690 | R11: =Tabla1[[#This Row],[Valor FOB (Free On Board)]]-Tabla1[[#This Row],[Costo total]] -> 2160 | S11: =Tabla1[[#This Row],[Utilidad]]/Tabla1[[#This Row],[Valor FOB (Free On Board)]] -> 0.36923077 | T11: =IF(Tabla1[[#This Row],[Margen]]>=30%,"Alta",IF(Tabla1[[#This Row],[Margen]]>=15%,"Media","Baja")) -> Alta | U11: =IF(Tabla1[[#This Row],[Valor FOB (Free On Board)]]>=10000,"Grande",IF(Tabla1[[#This Row],[Valor FOB (Free On Board)]]>=5000,"Mediana","Pequeña")) -> Mediana | V11: =IF(AND(Tabla1[[#This Row],[Clasificación Mercado]]="Estratégico", Tabla1[[#This Row],[Margen]]>=0.3), "Alta", IF(AND(Tabla1[[#This Row],[Clasificación Mercado]]="Estratégico", Tabla1[[#This Row],[Margen]]<0.3), "Media", IF(AND(Tabla1[[#This Row],[Clasificación Mercado]]="Potencial", Tabla1[[#This Row],[Margen]]>=0.3), "Media", "Baja"))) -> Alta
B12: EX008 | C12: 46099 | D12: Comercial Maya | E12: P004 | F12: Guatemala | G12: 750 | H12: 8.2 | I12: 5.9 | J12: Entregado | K12: =VLOOKUP(E:E,'2. Productos'!$C$3:$F$8,2,FALSE) -> Maní procesado | L12: =VLOOKUP(E:E,'2. Productos'!$C$3:$E$8,3,FALSE) -> Semillas | M12: =VLOOKUP(F:F,'3. Mercados'!$C$3:$F$9,2,FALSE) -> Centroamérica | N12: =VLOOKUP(F:F,'3. Mercados'!$C$3:$F$9,3,FALSE) -> 0.03 | O12: =VLOOKUP(F:F,'3. Mercados'!$C$3:$F$9,4,FALSE) -> Estratégico | P12: =Tabla1[[#This Row],[Unidades]]*Tabla1[[#This Row],[Precio FOB]] -> 6150 | Q12: =Tabla1[[#This Row],[Unidades]]*Tabla1[[#This Row],[Costo Unitario]] -> 4425 | R12: =Tabla1[[#This Row],[Valor FOB (Free On Board)]]-Tabla1[[#This Row],[Costo total]] -> 1725 | S12: =Tabla1[[#This Row],[Utilidad]]/Tabla1[[#This Row],[Valor FOB (Free On Board)]] -> 0.2804878 | T12: =IF(Tabla1[[#This Row],[Margen]]>=30%,"Alta",IF(Tabla1[[#This Row],[Margen]]>=15%,"Media","Baja")) -> Media | U12: =IF(Tabla1[[#This Row],[Valor FOB (Free On Board)]]>=10000,"Grande",IF(Tabla1[[#This Row],[Valor FOB (Free On Board)]]>=5000,"Mediana","Pequeña")) -> Mediana | V12: =IF(AND(Tabla1[[#This Row],[Clasificación Mercado]]="Estratégico", Tabla1[[#This Row],[Margen]]>=0.3), "Alta", IF(AND(Tabla1[[#This Row],[Clasificación Mercado]]="Estratégico", Tabla1[[#This Row],[Margen]]<0.3), "Media", IF(AND(Tabla1[[#This Row],[Clasificación Mercado]]="Potencial", Tabla1[[#This Row],[Margen]]>=0.3), "Media", "Baja"))) -> Media | Z12: ¿Cuál es el valor FOB total de las operaciones hacia México?
B13: EX009 | C13: 46106 | D13: Iberia Foods | E13: P005 | F13: España | G13: 600 | H13: 12.5 | I13: 8.7 | J13: Embarcado | K13: =VLOOKUP(E:E,'2. Productos'!$C$3:$F$8,2,FALSE) -> Aceite de ajonjolí | L13: =VLOOKUP(E:E,'2. Productos'!$C$3:$E$8,3,FALSE) -> Aceites | M13: =VLOOKUP(F:F,'3. Mercados'!$C$3:$F$9,2,FALSE) -> Europa | N13: =VLOOKUP(F:F,'3. Mercados'!$C$3:$F$9,3,FALSE) -> 0.1 | O13: =VLOOKUP(F:F,'3. Mercados'!$C$3:$F$9,4,FALSE) -> Potencial | P13: =Tabla1[[#This Row],[Unidades]]*Tabla1[[#This Row],[Precio FOB]] -> 7500 | Q13: =Tabla1[[#This Row],[Unidades]]*Tabla1[[#This Row],[Costo Unitario]] -> 5220 | R13: =Tabla1[[#This Row],[Valor FOB (Free On Board)]]-Tabla1[[#This Row],[Costo total]] -> 2280 | S13: =Tabla1[[#This Row],[Utilidad]]/Tabla1[[#This Row],[Valor FOB (Free On Board)]] -> 0.304 | T13: =IF(Tabla1[[#This Row],[Margen]]>=30%,"Alta",IF(Tabla1[[#This Row],[Margen]]>=15%,"Media","Baja")) -> Alta | U13: =IF(Tabla1[[#This Row],[Valor FOB (Free On Board)]]>=10000,"Grande",IF(Tabla1[[#This Row],[Valor FOB (Free On Board)]]>=5000,"Mediana","Pequeña")) -> Mediana | V13: =IF(AND(Tabla1[[#This Row],[Clasificación Mercado]]="Estratégico", Tabla1[[#This Row],[Margen]]>=0.3), "Alta", IF(AND(Tabla1[[#This Row],[Clasificación Mercado]]="Estratégico", Tabla1[[#This Row],[Margen]]<0.3), "Media", IF(AND(Tabla1[[#This Row],[Clasificación Mercado]]="Potencial", Tabla1[[#This Row],[Margen]]>=0.3), "Media", "Baja"))) -> Media | Z13: =SUMIF(Tabla1[País Destino],"México",Tabla1[Valor FOB (Free On Board)]) -> 120313
B14: EX010 | C14: 46114 | D14: Comercial Azteca | E14: P002 | F14: México | G14: 1100 | H14: 7.1 | I14: 4.8 | J14: Entregado | K14: =VLOOKUP(E:E,'2. Productos'!$C$3:$F$8,2,FALSE) -> Cacao en grano | L14: =VLOOKUP(E:E,'2. Productos'!$C$3:$E$8,3,FALSE) -> Cacao | M14: =VLOOKUP(F:F,'3. Mercados'!$C$3:$F$9,2,FALSE) -> Norteamérica | N14: =VLOOKUP(F:F,'3. Mercados'!$C$3:$F$9,3,FALSE) -> 0.08 | O14: =VLOOKUP(F:F,'3. Mercados'!$C$3:$F$9,4,FALSE) -> Potencial | P14: =Tabla1[[#This Row],[Unidades]]*Tabla1[[#This Row],[Precio FOB]] -> 7810 | Q14: =Tabla1[[#This Row],[Unidades]]*Tabla1[[#This Row],[Costo Unitario]] -> 5280 | R14: =Tabla1[[#This Row],[Valor FOB (Free On Board)]]-Tabla1[[#This Row],[Costo total]] -> 2530 | S14: =Tabla1[[#This Row],[Utilidad]]/Tabla1[[#This Row],[Valor FOB (Free On Board)]] -> 0.32394366 | T14: =IF(Tabla1[[#This Row],[Margen]]>=30%,"Alta",IF(Tabla1[[#This Row],[Margen]]>=15%,"Media","Baja")) -> Alta | U14: =IF(Tabla1[[#This Row],[Valor FOB (Free On Board)]]>=10000,"Grande",IF(Tabla1[[#This Row],[Valor FOB (Free On Board)]]>=5000,"Mediana","Pequeña")) -> Mediana | V14: =IF(AND(Tabla1[[#This Row],[Clasificación Mercado]]="Estratégico", Tabla1[[#This Row],[Margen]]>=0.3), "Alta", IF(AND(Tabla1[[#This Row],[Clasificación Mercado]]="Estratégico", Tabla1[[#This Row],[Margen]]<0.3), "Media", IF(AND(Tabla1[[#This Row],[Clasificación Mercado]]="Potencial", Tabla1[[#This Row],[Margen]]>=0.3), "Media", "Baja"))) -> Media
B15: EX011 | C15: 46122 | D15: Global Foods | E15: P004 | F15: EE.UU. | G15: 1300 | H15: 8.2 | I15: 5.9 | J15: Entregado | K15: =VLOOKUP(E:E,'2. Productos'!$C$3:$F$8,2,FALSE) -> Maní procesado | L15: =VLOOKUP(E:E,'2. Productos'!$C$3:$E$8,3,FALSE) -> Semillas | M15: =VLOOKUP(F:F,'3. Mercados'!$C$3:$F$9,2,FALSE) -> Norteamérica | N15: =VLOOKUP(F:F,'3. Mercados'!$C$3:$F$9,3,FALSE) -> 0.05 | O15: =VLOOKUP(F:F,'3. Mercados'!$C$3:$F$9,4,FALSE) -> Estratégico | P15: =Tabla1[[#This Row],[Unidades]]*Tabla1[[#This Row],[Precio FOB]] -> 10660 | Q15: =Tabla1[[#This Row],[Unidades]]*Tabla1[[#This Row],[Costo Unitario]] -> 7670 | R15: =Tabla1[[#This Row],[Valor FOB (Free On Board)]]-Tabla1[[#This Row],[Costo total]] -> 2990 | S15: =Tabla1[[#This Row],[Utilidad]]/Tabla1[[#This Row],[Valor FOB (Free On Board)]] -> 0.2804878 | T15: =IF(Tabla1[[#This Row],[Margen]]>=30%,"Alta",IF(Tabla1[[#This Row],[Margen]]>=15%,"Media","Baja")) -> Media | U15: =IF(Tabla1[[#This Row],[Valor FOB (Free On Board)]]>=10000,"Grande",IF(Tabla1[[#This Row],[Valor FOB (Free On Board)]]>=5000,"Mediana","Pequeña")) -> Grande | V15: =IF(AND(Tabla1[[#This Row],[Clasificación Mercado]]="Estratégico", Tabla1[[#This Row],[Margen]]>=0.3), "Alta", IF(AND(Tabla1[[#This Row],[Clasificación Mercado]]="Estratégico", Tabla1[[#This Row],[Margen]]<0.3), "Media", IF(AND(Tabla1[[#This Row],[Clasificación Mercado]]="Potencial", Tabla1[[#This Row],[Margen]]>=0.3), "Media", "Baja"))) -> Media | Z15: ¿Cuál es el total de unidades exportadas hacia Guatemala?
B16: EX012 | C16: 46130 | D16: Comercial Maya | E16: P001 | F16: Guatemala | G16: 700 | H16: 6.5 | I16: 4.1 | J16: Pendiente | K16: =VLOOKUP(E:E,'2. Productos'!$C$3:$F$8,2,FALSE) -> Café especial | L16: =VLOOKUP(E:E,'2. Productos'!$C$3:$E$8,3,FALSE) -> Café | M16: =VLOOKUP(F:F,'3. Mercados'!$C$3:$F$9,2,FALSE) -> Centroamérica | N16: =VLOOKUP(F:F,'3. Mercados'!$C$3:$F$9,3,FALSE) -> 0.03 | O16: =VLOOKUP(F:F,'3. Mercados'!$C$3:$F$9,4,FALSE) -> Estratégico | P16: =Tabla1[[#This Row],[Unidades]]*Tabla1[[#This Row],[Precio FOB]] -> 4550 | Q16: =Tabla1[[#This Row],[Unidades]]*Tabla1[[#This Row],[Costo Unitario]] -> 2870 | R16: =Tabla1[[#This Row],[Valor FOB (Free On Board)]]-Tabla1[[#This Row],[Costo total]] -> 1680 | S16: =Tabla1[[#This Row],[Utilidad]]/Tabla1[[#This Row],[Valor FOB (Free On Board)]] -> 0.36923077 | T16: =IF(Tabla1[[#This Row],[Margen]]>=30%,"Alta",IF(Tabla1[[#This Row],[Margen]]>=15%,"Media","Baja")) -> Alta | U16: =IF(Tabla1[[#This Row],[Valor FOB (Free On Board)]]>=10000,"Grande",IF(Tabla1[[#This Row],[Valor FOB (Free On Board)]]>=5000,"Mediana","Pequeña")) -> Pequeña | V16: =IF(AND(Tabla1[[#This Row],[Clasificación Mercado]]="Estratégico", Tabla1[[#This Row],[Margen]]>=0.3), "Alta", IF(AND(Tabla1[[#This Row],[Clasificación Mercado]]="Estratégico", Tabla1[[#This Row],[Margen]]<0.3), "Media", IF(AND(Tabla1[[#This Row],[Clasificación Mercado]]="Potencial", Tabla1[[#This Row],[Margen]]>=0.3), "Media", "Baja"))) -> Alta | Z16: =SUMIF(Tabla1[País Destino],"Guatemala",G5:G103) -> 17130
B17: EX013 | C17: 46139 | D17: Distribuidora Tica | E17: P005 | F17: Costa Rica | G17: 450 | H17: 12.5 | I17: 8.7 | J17: Embarcado | K17: =VLOOKUP(E:E,'2. Productos'!$C$3:$F$8,2,FALSE) -> Aceite de ajonjolí | L17: =VLOOKUP(E:E,'2. Productos'!$C$3:$E$8,3,FALSE) -> Aceites | M17: =VLOOKUP(F:F,'3. Mercados'!$C$3:$F$9,2,FALSE) -> Centroamérica | N17: =VLOOKUP(F:F,'3. Mercados'!$C$3:$F$9,3,FALSE) -> 0.02 | O17: =VLOOKUP(F:F,'3. Mercados'!$C$3:$F$9,4,FALSE) -> Estratégico | P17: =Tabla1[[#This Row],[Unidades]]*Tabla1[[#This Row],[Precio FOB]] -> 5625 | Q17: =Tabla1[[#This Row],[Unidades]]*Tabla1[[#This Row],[Costo Unitario]] -> 3915 | R17: =Tabla1[[#This Row],[Valor FOB (Free On Board)]]-Tabla1[[#This Row],[Costo total]] -> 1710 | S17: =Tabla1[[#This Row],[Utilidad]]/Tabla1[[#This Row],[Valor FOB (Free On Board)]] -> 0.304 | T17: =IF(Tabla1[[#This Row],[Margen]]>=30%,"Alta",IF(Tabla1[[#This Row],[Margen]]>=15%,"Media","Baja")) -> Alta | U17: =IF(Tabla1[[#This Row],[Valor FOB (Free On Board)]]>=10000,"Grande",IF(Tabla1[[#This Row],[Valor FOB (Free On Board)]]>=5000,"Mediana","Pequeña")) -> Mediana | V17: =IF(AND(Tabla1[[#This Row],[Clasificación Mercado]]="Estratégico", Tabla1[[#This Row],[Margen]]>=0.3), "Alta", IF(AND(Tabla1[[#This Row],[Clasificación Mercado]]="Estratégico", Tabla1[[#This Row],[Margen]]<0.3), "Media", IF(AND(Tabla1[[#This Row],[Clasificación Mercado]]="Potencial", Tabla1[[#This Row],[Margen]]>=0.3), "Media", "Baja"))) -> Alta
B18: EX014 | C18: 46147 | D18: Iberia Foods | E18: P003 | F18: España | G18: 1000 | H18: 4.8 | I18: 3.2 | J18: Entregado | K18: =VLOOKUP(E:E,'2. Productos'!$C$3:$F$8,2,FALSE) -> Miel natural | L18: =VLOOKUP(E:E,'2. Productos'!$C$3:$E$8,3,FALSE) -> Apícola | M18: =VLOOKUP(F:F,'3. Mercados'!$C$3:$F$9,2,FALSE) -> Europa | N18: =VLOOKUP(F:F,'3. Mercados'!$C$3:$F$9,3,FALSE) -> 0.1 | O18: =VLOOKUP(F:F,'3. Mercados'!$C$3:$F$9,4,FALSE) -> Potencial | P18: =Tabla1[[#This Row],[Unidades]]*Tabla1[[#This Row],[Precio FOB]] -> 4800 | Q18: =Tabla1[[#This Row],[Unidades]]*Tabla1[[#This Row],[Costo Unitario]] -> 3200 | R18: =Tabla1[[#This Row],[Valor FOB (Free On Board)]]-Tabla1[[#This Row],[Costo total]] -> 1600 | S18: =Tabla1[[#This Row],[Utilidad]]/Tabla1[[#This Row],[Valor FOB (Free On Board)]] -> 0.33333333 | T18: =IF(Tabla1[[#This Row],[Margen]]>=30%,"Alta",IF(Tabla1[[#This Row],[Margen]]>=15%,"Media","Baja")) -> Alta | U18: =IF(Tabla1[[#This Row],[Valor FOB (Free On Board)]]>=10000,"Grande",IF(Tabla1[[#This Row],[Valor FOB (Free On Board)]]>=5000,"Mediana","Pequeña")) -> Pequeña | V18: =IF(AND(Tabla1[[#This Row],[Clasificación Mercado]]="Estratégico", Tabla1[[#This Row],[Margen]]>=0.3), "Alta", IF(AND(Tabla1[[#This Row],[Clasificación Mercado]]="Estratégico", Tabla1[[#This Row],[Margen]]<0.3), "Media", IF(AND(Tabla1[[#This Row],[Clasificación Mercado]]="Potencial", Tabla1[[#This Row],[Margen]]>=0.3), "Media", "Baja"))) -> Media | Z18: ¿Cuál es el valor FOB de las operaciones de Café especial enviadas a Estados Unidos?
B19: EX015 | C19: 46156 | D19: Comercial Azteca | E19: P001 | F19: México | G19: 850 | H19: 6.5 | I19: 4.1 | J19: Embarcado | K19: =VLOOKUP(E:E,'2. Productos'!$C$3:$F$8,2,FALSE) -> Café especial | L19: =VLOOKUP(E:E,'2. Productos'!$C$3:$E$8,3,FALSE) -> Café | M19: =VLOOKUP(F:F,'3. Mercados'!$C$3:$F$9,2,FALSE) -> Norteamérica | N19: =VLOOKUP(F:F,'3. Mercados'!$C$3:$F$9,3,FALSE) -> 0.08 | O19: =VLOOKUP(F:F,'3. Mercados'!$C$3:$F$9,4,FALSE) -> Potencial | P19: =Tabla1[[#This Row],[Unidades]]*Tabla1[[#This Row],[Precio FOB]] -> 5525 | Q19: =Tabla1[[#This Row],[Unidades]]*Tabla1[[#This Row],[Costo Unitario]] -> 3485 | R19: =Tabla1[[#This Row],[Valor FOB (Free On Board)]]-Tabla1[[#This Row],[Costo total]] -> 2040 | S19: =Tabla1[[#This Row],[Utilidad]]/Tabla1[[#This Row],[Valor FOB (Free On Board)]] -> 0.36923077 | T19: =IF(Tabla1[[#This Row],[Margen]]>=30%,"Alta",IF(Tabla1[[#This Row],[Margen]]>=15%,"Media","Baja")) -> Alta | U19: =IF(Tabla1[[#This Row],[Valor FOB (Free On Board)]]>=10000,"Grande",IF(Tabla1[[#This Row],[Valor FOB (Free On Board)]]>=5000,"Mediana","Pequeña")) -> Mediana | V19: =IF(AND(Tabla1[[#This Row],[Clasificación Mercado]]="Estratégico", Tabla1[[#This Row],[Margen]]>=0.3), "Alta", IF(AND(Tabla1[[#This Row],[Clasificación Mercado]]="Estratégico", Tabla1[[#This Row],[Margen]]<0.3), "Media", IF(AND(Tabla1[[#This Row],[Clasificación Mercado]]="Potencial", Tabla1[[#This Row],[Margen]]>=0.3), "Media", "Baja"))) -> Media | Z19: =SUMIFS(Tabla1[Valor FOB (Free On Board)],Tabla1[producto],"Café especial",Tabla1[País Destino],"EE.UU.") -> 52390
B20: EX016 | C20: 46164 | D20: Global Foods | E20: P002 | F20: EE.UU. | G20: 1250 | H20: 7.1 | I20: 4.8 | J20: Entregado | K20: =VLOOKUP(E:E,'2. Productos'!$C$3:$F$8,2,FALSE) -> Cacao en grano | L20: =VLOOKUP(E:E,'2. Productos'!$C$3:$E$8,3,FALSE) -> Cacao | M20: =VLOOKUP(F:F,'3. Mercados'!$C$3:$F$9,2,FALSE) -> Norteamérica | N20: =VLOOKUP(F:F,'3. Mercados'!$C$3:$F$9,3,FALSE) -> 0.05 | O20: =VLOOKUP(F:F,'3. Mercados'!$C$3:$F$9,4,FALSE) -> Estratégico | P20: =Tabla1[[#This Row],[Unidades]]*Tabla1[[#This Row],[Precio FOB]] -> 8875 | Q20: =Tabla1[[#This Row],[Unidades]]*Tabla1[[#This Row],[Costo Unitario]] -> 6000 | R20: =Tabla1[[#This Row],[Valor FOB (Free On Board)]]-Tabla1[[#This Row],[Costo total]] -> 2875 | S20: =Tabla1[[#This Row],[Utilidad]]/Tabla1[[#This Row],[Valor FOB (Free On Board)]] -> 0.32394366 | T20: =IF(Tabla1[[#This Row],[Margen]]>=30%,"Alta",IF(Tabla1[[#This Row],[Margen]]>=15%,"Media","Baja")) -> Alta | U20: =IF(Tabla1[[#This Row],[Valor FOB (Free On Board)]]>=10000,"Grande",IF(Tabla1[[#This Row],[Valor FOB (Free On Board)]]>=5000,"Mediana","Pequeña")) -> Mediana | V20: =IF(AND(Tabla1[[#This Row],[Clasificación Mercado]]="Estratégico", Tabla1[[#This Row],[Margen]]>=0.3), "Alta", IF(AND(Tabla1[[#This Row],[Clasificación Mercado]]="Estratégico", Tabla1[[#This Row],[Margen]]<0.3), "Media", IF(AND(Tabla1[[#This Row],[Clasificación Mercado]]="Potencial", Tabla1[[#This Row],[Margen]]>=0.3), "Media", "Baja"))) -> Alta
B21: EX017 | C21: 46172 | D21: Comercial Maya | E21: P005 | F21: Guatemala | G21: 550 | H21: 12.5 | I21: 8.7 | J21: Embarcado | K21: =VLOOKUP(E:E,'2. Productos'!$C$3:$F$8,2,FALSE) -> Aceite de ajonjolí | L21: =VLOOKUP(E:E,'2. Productos'!$C$3:$E$8,3,FALSE) -> Aceites | M21: =VLOOKUP(F:F,'3. Mercados'!$C$3:$F$9,2,FALSE) -> Centroamérica | N21: =VLOOKUP(F:F,'3. Mercados'!$C$3:$F$9,3,FALSE) -> 0.03 | O21: =VLOOKUP(F:F,'3. Mercados'!$C$3:$F$9,4,FALSE) -> Estratégico | P21: =Tabla1[[#This Row],[Unidades]]*Tabla1[[#This Row],[Precio FOB]] -> 6875 | Q21: =Tabla1[[#This Row],[Unidades]]*Tabla1[[#This Row],[Costo Unitario]] -> 4785 | R21: =Tabla1[[#This Row],[Valor FOB (Free On Board)]]-Tabla1[[#This Row],[Costo total]] -> 2090 | S21: =Tabla1[[#This Row],[Utilidad]]/Tabla1[[#This Row],[Valor FOB (Free On Board)]] -> 0.304 | T21: =IF(Tabla1[[#This Row],[Margen]]>=30%,"Alta",IF(Tabla1[[#This Row],[Margen]]>=15%,"Media","Baja")) -> Alta | U21: =IF(Tabla1[[#This Row],[Valor FOB (Free On Board)]]>=10000,"Grande",IF(Tabla1[[#This Row],[Valor FOB (Free On Board)]]>=5000,"Mediana","Pequeña")) -> Mediana | V21: =IF(AND(Tabla1[[#This Row],[Clasificación Mercado]]="Estratégico", Tabla1[[#This Row],[Margen]]>=0.3), "Alta", IF(AND(Tabla1[[#This Row],[Clasificación Mercado]]="Estratégico", Tabla1[[#This Row],[Margen]]<0.3), "Media", IF(AND(Tabla1[[#This Row],[Clasificación Mercado]]="Potencial", Tabla1[[#This Row],[Margen]]>=0.3), "Media", "Baja"))) -> Alta | Z21: ¿Cuál es la utilidad obtenida de las operaciones entregadas a clientes de Centroamérica?
B22: EX018 | C22: 46180 | D22: Distribuidora Tica | E22: P003 | F22: Costa Rica | G22: 800 | H22: 4.8 | I22: 3.2 | J22: Entregado | K22: =VLOOKUP(E:E,'2. Productos'!$C$3:$F$8,2,FALSE) -> Miel natural | L22: =VLOOKUP(E:E,'2. Productos'!$C$3:$E$8,3,FALSE) -> Apícola | M22: =VLOOKUP(F:F,'3. Mercados'!$C$3:$F$9,2,FALSE) -> Centroamérica | N22: =VLOOKUP(F:F,'3. Mercados'!$C$3:$F$9,3,FALSE) -> 0.02 | O22: =VLOOKUP(F:F,'3. Mercados'!$C$3:$F$9,4,FALSE) -> Estratégico | P22: =Tabla1[[#This Row],[Unidades]]*Tabla1[[#This Row],[Precio FOB]] -> 3840 | Q22: =Tabla1[[#This Row],[Unidades]]*Tabla1[[#This Row],[Costo Unitario]] -> 2560 | R22: =Tabla1[[#This Row],[Valor FOB (Free On Board)]]-Tabla1[[#This Row],[Costo total]] -> 1280 | S22: =Tabla1[[#This Row],[Utilidad]]/Tabla1[[#This Row],[Valor FOB (Free On Board)]] -> 0.33333333 | T22: =IF(Tabla1[[#This Row],[Margen]]>=30%,"Alta",IF(Tabla1[[#This Row],[Margen]]>=15%,"Media","Baja")) -> Alta | U22: =IF(Tabla1[[#This Row],[Valor FOB (Free On Board)]]>=10000,"Grande",IF(Tabla1[[#This Row],[Valor FOB (Free On Board)]]>=5000,"Mediana","Pequeña")) -> Pequeña | V22: =IF(AND(Tabla1[[#This Row],[Clasificación Mercado]]="Estratégico", Tabla1[[#This Row],[Margen]]>=0.3), "Alta", IF(AND(Tabla1[[#This Row],[Clasificación Mercado]]="Estratégico", Tabla1[[#This Row],[Margen]]<0.3), "Media", IF(AND(Tabla1[[#This Row],[Clasificación Mercado]]="Potencial", Tabla1[[#This Row],[Margen]]>=0.3), "Media", "Baja"))) -> Alta | Z22: =SUMIFS(Tabla1[Utilidad],Tabla1[Región],"Centroamérica",Tabla1[Estado],"Entregado") -> 33348
B23: EX019 | C23: 46189 | D23: Iberia Foods | E23: P004 | F23: España | G23: 900 | H23: 8.2 | I23: 5.9 | J23: Pendiente | K23: =VLOOKUP(E:E,'2. Productos'!$C$3:$F$8,2,FALSE) -> Maní procesado | L23: =VLOOKUP(E:E,'2. Productos'!$C$3:$E$8,3,FALSE) -> Semillas | M23: =VLOOKUP(F:F,'3. Mercados'!$C$3:$F$9,2,FALSE) -> Europa | N23: =VLOOKUP(F:F,'3. Mercados'!$C$3:$F$9,3,FALSE) -> 0.1 | O23: =VLOOKUP(F:F,'3. Mercados'!$C$3:$F$9,4,FALSE) -> Potencial | P23: =Tabla1[[#This Row],[Unidades]]*Tabla1[[#This Row],[Precio FOB]] -> 7380 | Q23: =Tabla1[[#This Row],[Unidades]]*Tabla1[[#This Row],[Costo Unitario]] -> 5310 | R23: =Tabla1[[#This Row],[Valor FOB (Free On Board)]]-Tabla1[[#This Row],[Costo total]] -> 2070 | S23: =Tabla1[[#This Row],[Utilidad]]/Tabla1[[#This Row],[Valor FOB (Free On Board)]] -> 0.2804878 | T23: =IF(Tabla1[[#This Row],[Margen]]>=30%,"Alta",IF(Tabla1[[#This Row],[Margen]]>=15%,"Media","Baja")) -> Media | U23: =IF(Tabla1[[#This Row],[Valor FOB (Free On Board)]]>=10000,"Grande",IF(Tabla1[[#This Row],[Valor FOB (Free On Board)]]>=5000,"Mediana","Pequeña")) -> Mediana | V23: =IF(AND(Tabla1[[#This Row],[Clasificación Mercado]]="Estratégico", Tabla1[[#This Row],[Margen]]>=0.3), "Alta", IF(AND(Tabla1[[#This Row],[Clasificación Mercado]]="Estratégico", Tabla1[[#This Row],[Margen]]<0.3), "Media", IF(AND(Tabla1[[#This Row],[Clasificación Mercado]]="Potencial", Tabla1[[#This Row],[Margen]]>=0.3), "Media", "Baja"))) -> Baja
B24: EX020 | C24: 46198 | D24: Comercial Azteca | E24: P005 | F24: México | G24: 650 | H24: 12.5 | I24: 8.7 | J24: Entregado | K24: =VLOOKUP(E:E,'2. Productos'!$C$3:$F$8,2,FALSE) -> Aceite de ajonjolí | L24: =VLOOKUP(E:E,'2. Productos'!$C$3:$E$8,3,FALSE) -> Aceites | M24: =VLOOKUP(F:F,'3. Mercados'!$C$3:$F$9,2,FALSE) -> Norteamérica | N24: =VLOOKUP(F:F,'3. Mercados'!$C$3:$F$9,3,FALSE) -> 0.08 | O24: =VLOOKUP(F:F,'3. Mercados'!$C$3:$F$9,4,FALSE) -> Potencial | P24: =Tabla1[[#This Row],[Unidades]]*Tabla1[[#This Row],[Precio FOB]] -> 8125 | Q24: =Tabla1[[#This Row],[Unidades]]*Tabla1[[#This Row],[Costo Unitario]] -> 5655 | R24: =Tabla1[[#This Row],[Valor FOB (Free On Board)]]-Tabla1[[#This Row],[Costo total]] -> 2470 | S24: =Tabla1[[#This Row],[Utilidad]]/Tabla1[[#This Row],[Valor FOB (Free On Board)]] -> 0.304 | T24: =IF(Tabla1[[#This Row],[Margen]]>=30%,"Alta",IF(Tabla1[[#This Row],[Margen]]>=15%,"Media","Baja")) -> Alta | U24: =IF(Tabla1[[#This Row],[Valor FOB (Free On Board)]]>=10000,"Grande",IF(Tabla1[[#This Row],[Valor FOB (Free On Board)]]>=5000,"Mediana","Pequeña")) -> Mediana | V24: =IF(AND(Tabla1[[#This Row],[Clasificación Mercado]]="Estratégico", Tabla1[[#This Row],[Margen]]>=0.3), "Alta", IF(AND(Tabla1[[#This Row],[Clasificación Mercado]]="Estratégico", Tabla1[[#This Row],[Margen]]<0.3), "Media", IF(AND(Tabla1[[#This Row],[Clasificación Mercado]]="Potencial", Tabla1[[#This Row],[Margen]]>=0.3), "Media", "Baja"))) -> Media
B25: EX021 | C25: 46206 | D25: Global Foods | E25: P001 | F25: EE.UU. | G25: 1500 | H25: 6.5 | I25: 4.1 | J25: Embarcado | K25: =VLOOKUP(E:E,'2. Productos'!$C$3:$F$8,2,FALSE) -> Café especial | L25: =VLOOKUP(E:E,'2. Productos'!$C$3:$E$8,3,FALSE) -> Café | M25: =VLOOKUP(F:F,'3. Mercados'!$C$3:$F$9,2,FALSE) -> Norteamérica | N25: =VLOOKUP(F:F,'3. Mercados'!$C$3:$F$9,3,FALSE) -> 0.05 | O25: =VLOOKUP(F:F,'3. Mercados'!$C$3:$F$9,4,FALSE) -> Estratégico | P25: =Tabla1[[#This Row],[Unidades]]*Tabla1[[#This Row],[Precio FOB]] -> 9750 | Q25: =Tabla1[[#This Row],[Unidades]]*Tabla1[[#This Row],[Costo Unitario]] -> 6150 | R25: =Tabla1[[#This Row],[Valor FOB (Free On Board)]]-Tabla1[[#This Row],[Costo total]] -> 3600 | S25: =Tabla1[[#This Row],[Utilidad]]/Tabla1[[#This Row],[Valor FOB (Free On Board)]] -> 0.36923077 | T25: =IF(Tabla1[[#This Row],[Margen]]>=30%,"Alta",IF(Tabla1[[#This Row],[Margen]]>=15%,"Media","Baja")) -> Alta | U25: =IF(Tabla1[[#This Row],[Valor FOB (Free On Board)]]>=10000,"Grande",IF(Tabla1[[#This Row],[Valor FOB (Free On Board)]]>=5000,"Mediana","Pequeña")) -> Mediana | V25: =IF(AND(Tabla1[[#This Row],[Clasificación Mercado]]="Estratégico", Tabla1[[#This Row],[Margen]]>=0.3), "Alta", IF(AND(Tabla1[[#This Row],[Clasificación Mercado]]="Estratégico", Tabla1[[#This Row],[Margen]]<0.3), "Media", IF(AND(Tabla1[[#This Row],[Clasificación Mercado]]="Potencial", Tabla1[[#This Row],[Margen]]>=0.3), "Media", "Baja"))) -> Alta
B26: EX022 | C26: 46214 | D26: Comercial Maya | E26: P002 | F26: Guatemala | G26: 1000 | H26: 7.1 | I26: 4.8 | J26: Entregado | K26: =VLOOKUP(E:E,'2. Productos'!$C$3:$F$8,2,FALSE) -> Cacao en grano | L26: =VLOOKUP(E:E,'2. Productos'!$C$3:$E$8,3,FALSE) -> Cacao | M26: =VLOOKUP(F:F,'3. Mercados'!$C$3:$F$9,2,FALSE) -> Centroamérica | N26: =VLOOKUP(F:F,'3. Mercados'!$C$3:$F$9,3,FALSE) -> 0.03 | O26: =VLOOKUP(F:F,'3. Mercados'!$C$3:$F$9,4,FALSE) -> Estratégico | P26: =Tabla1[[#This Row],[Unidades]]*Tabla1[[#This Row],[Precio FOB]] -> 7100 | Q26: =Tabla1[[#This Row],[Unidades]]*Tabla1[[#This Row],[Costo Unitario]] -> 4800 | R26: =Tabla1[[#This Row],[Valor FOB (Free On Board)]]-Tabla1[[#This Row],[Costo total]] -> 2300 | S26: =Tabla1[[#This Row],[Utilidad]]/Tabla1[[#This Row],[Valor FOB (Free On Board)]] -> 0.32394366 | T26: =IF(Tabla1[[#This Row],[Margen]]>=30%,"Alta",IF(Tabla1[[#This Row],[Margen]]>=15%,"Media","Baja")) -> Alta | U26: =IF(Tabla1[[#This Row],[Valor FOB (Free On Board)]]>=10000,"Grande",IF(Tabla1[[#This Row],[Valor FOB (Free On Board)]]>=5000,"Mediana","Pequeña")) -> Mediana | V26: =IF(AND(Tabla1[[#This Row],[Clasificación Mercado]]="Estratégico", Tabla1[[#This Row],[Margen]]>=0.3), "Alta", IF(AND(Tabla1[[#This Row],[Clasificación Mercado]]="Estratégico", Tabla1[[#This Row],[Margen]]<0.3), "Media", IF(AND(Tabla1[[#This Row],[Clasificación Mercado]]="Potencial", Tabla1[[#This Row],[Margen]]>=0.3), "Media", "Baja"))) -> Alta
B27: EX023 | C27: 46222 | D27: Distribuidora Tica | E27: P004 | F27: Costa Rica | G27: 720 | H27: 8.2 | I27: 5.9 | J27: Embarcado | K27: =VLOOKUP(E:E,'2. Productos'!$C$3:$F$8,2,FALSE) -> Maní procesado | L27: =VLOOKUP(E:E,'2. Productos'!$C$3:$E$8,3,FALSE) -> Semillas | M27: =VLOOKUP(F:F,'3. Mercados'!$C$3:$F$9,2,FALSE) -> Centroamérica | N27: =VLOOKUP(F:F,'3. Mercados'!$C$3:$F$9,3,FALSE) -> 0.02 | O27: =VLOOKUP(F:F,'3. Mercados'!$C$3:$F$9,4,FALSE) -> Estratégico | P27: =Tabla1[[#This Row],[Unidades]]*Tabla1[[#This Row],[Precio FOB]] -> 5904 | Q27: =Tabla1[[#This Row],[Unidades]]*Tabla1[[#This Row],[Costo Unitario]] -> 4248 | R27: =Tabla1[[#This Row],[Valor FOB (Free On Board)]]-Tabla1[[#This Row],[Costo total]] -> 1656 | S27: =Tabla1[[#This Row],[Utilidad]]/Tabla1[[#This Row],[Valor FOB (Free On Board)]] -> 0.2804878 | T27: =IF(Tabla1[[#This Row],[Margen]]>=30%,"Alta",IF(Tabla1[[#This Row],[Margen]]>=15%,"Media","Baja")) -> Media | U27: =IF(Tabla1[[#This Row],[Valor FOB (Free On Board)]]>=10000,"Grande",IF(Tabla1[[#This Row],[Valor FOB (Free On Board)]]>=5000,"Mediana","Pequeña")) -> Mediana | V27: =IF(AND(Tabla1[[#This Row],[Clasificación Mercado]]="Estratégico", Tabla1[[#This Row],[Margen]]>=0.3), "Alta", IF(AND(Tabla1[[#This Row],[Clasificación Mercado]]="Estratégico", Tabla1[[#This Row],[Margen]]<0.3), "Media", IF(AND(Tabla1[[#This Row],[Clasificación Mercado]]="Potencial", Tabla1[[#This Row],[Margen]]>=0.3), "Media", "Baja"))) -> Media
B28: EX024 | C28: 46231 | D28: Iberia Foods | E28: P003 | F28: España | G28: 1150 | H28: 4.8 | I28: 3.2 | J28: Entregado | K28: =VLOOKUP(E:E,'2. Productos'!$C$3:$F$8,2,FALSE) -> Miel natural | L28: =VLOOKUP(E:E,'2. Productos'!$C$3:$E$8,3,FALSE) -> Apícola | M28: =VLOOKUP(F:F,'3. Mercados'!$C$3:$F$9,2,FALSE) -> Europa | N28: =VLOOKUP(F:F,'3. Mercados'!$C$3:$F$9,3,FALSE) -> 0.1 | O28: =VLOOKUP(F:F,'3. Mercados'!$C$3:$F$9,4,FALSE) -> Potencial | P28: =Tabla1[[#This Row],[Unidades]]*Tabla1[[#This Row],[Precio FOB]] -> 5520 | Q28: =Tabla1[[#This Row],[Unidades]]*Tabla1[[#This Row],[Costo Unitario]] -> 3680 | R28: =Tabla1[[#This Row],[Valor FOB (Free On Board)]]-Tabla1[[#This Row],[Costo total]] -> 1840 | S28: =Tabla1[[#This Row],[Utilidad]]/Tabla1[[#This Row],[Valor FOB (Free On Board)]] -> 0.33333333 | T28: =IF(Tabla1[[#This Row],[Margen]]>=30%,"Alta",IF(Tabla1[[#This Row],[Margen]]>=15%,"Media","Baja")) -> Alta | U28: =IF(Tabla1[[#This Row],[Valor FOB (Free On Board)]]>=10000,"Grande",IF(Tabla1[[#This Row],[Valor FOB (Free On Board)]]>=5000,"Mediana","Pequeña")) -> Mediana | V28: =IF(AND(Tabla1[[#This Row],[Clasificación Mercado]]="Estratégico", Tabla1[[#This Row],[Margen]]>=0.3), "Alta", IF(AND(Tabla1[[#This Row],[Clasificación Mercado]]="Estratégico", Tabla1[[#This Row],[Margen]]<0.3), "Media", IF(AND(Tabla1[[#This Row],[Clasificación Mercado]]="Potencial", Tabla1[[#This Row],[Margen]]>=0.3), "Media", "Baja"))) -> Media
B29: EX025 | C29: 46239 | D29: Comercial Azteca | E29: P001 | F29: México | G29: 950 | H29: 6.5 | I29: 4.1 | J29: Pendiente | K29: =VLOOKUP(E:E,'2. Productos'!$C$3:$F$8,2,FALSE) -> Café especial | L29: =VLOOKUP(E:E,'2. Productos'!$C$3:$E$8,3,FALSE) -> Café | M29: =VLOOKUP(F:F,'3. Mercados'!$C$3:$F$9,2,FALSE) -> Norteamérica | N29: =VLOOKUP(F:F,'3. Mercados'!$C$3:$F$9,3,FALSE) -> 0.08 | O29: =VLOOKUP(F:F,'3. Mercados'!$C$3:$F$9,4,FALSE) -> Potencial | P29: =Tabla1[[#This Row],[Unidades]]*Tabla1[[#This Row],[Precio FOB]] -> 6175 | Q29: =Tabla1[[#This Row],[Unidades]]*Tabla1[[#This Row],[Costo Unitario]] -> 3895 | R29: =Tabla1[[#This Row],[Valor FOB (Free On Board)]]-Tabla1[[#This Row],[Costo total]] -> 2280 | S29: =Tabla1[[#This Row],[Utilidad]]/Tabla1[[#This Row],[Valor FOB (Free On Board)]] -> 0.36923077 | T29: =IF(Tabla1[[#This Row],[Margen]]>=30%,"Alta",IF(Tabla1[[#This Row],[Margen]]>=15%,"Media","Baja")) -> Alta | U29: =IF(Tabla1[[#This Row],[Valor FOB (Free On Board)]]>=10000,"Grande",IF(Tabla1[[#This Row],[Valor FOB (Free On Board)]]>=5000,"Mediana","Pequeña")) -> Mediana | V29: =IF(AND(Tabla1[[#This Row],[Clasificación Mercado]]="Estratégico", Tabla1[[#This Row],[Margen]]>=0.3), "Alta", IF(AND(Tabla1[[#This Row],[Clasificación Mercado]]="Estratégico", Tabla1[[#This Row],[Margen]]<0.3), "Media", IF(AND(Tabla1[[#This Row],[Clasificación Mercado]]="Potencial", Tabla1[[#This Row],[Margen]]>=0.3), "Media", "Baja"))) -> Media
B30: EX026 | C30: 46247 | D30: Global Foods | E30: P005 | F30: EE.UU. | G30: 700 | H30: 12.5 | I30: 8.7 | J30: Entregado | K30: =VLOOKUP(E:E,'2. Productos'!$C$3:$F$8,2,FALSE) -> Aceite de ajonjolí | L30: =VLOOKUP(E:E,'2. Productos'!$C$3:$E$8,3,FALSE) -> Aceites | M30: =VLOOKUP(F:F,'3. Mercados'!$C$3:$F$9,2,FALSE) -> Norteamérica | N30: =VLOOKUP(F:F,'3. Mercados'!$C$3:$F$9,3,FALSE) -> 0.05 | O30: =VLOOKUP(F:F,'3. Mercados'!$C$3:$F$9,4,FALSE) -> Estratégico | P30: =Tabla1[[#This Row],[Unidades]]*Tabla1[[#This Row],[Precio FOB]] -> 8750 | Q30: =Tabla1[[#This Row],[Unidades]]*Tabla1[[#This Row],[Costo Unitario]] -> 6090 | R30: =Tabla1[[#This Row],[Valor FOB (Free On Board)]]-Tabla1[[#This Row],[Costo total]] -> 2660 | S30: =Tabla1[[#This Row],[Utilidad]]/Tabla1[[#This Row],[Valor FOB (Free On Board)]] -> 0.304 | T30: =IF(Tabla1[[#This Row],[Margen]]>=30%,"Alta",IF(Tabla1[[#This Row],[Margen]]>=15%,"Media","Baja")) -> Alta | U30: =IF(Tabla1[[#This Row],[Valor FOB (Free On Board)]]>=10000,"Grande",IF(Tabla1[[#This Row],[Valor FOB (Free On Board)]]>=5000,"Mediana","Pequeña")) -> Mediana | V30: =IF(AND(Tabla1[[#This Row],[Clasificación Mercado]]="Estratégico", Tabla1[[#This Row],[Margen]]>=0.3), "Alta", IF(AND(Tabla1[[#This Row],[Clasificación Mercado]]="Estratégico", Tabla1[[#This Row],[Margen]]<0.3), "Media", IF(AND(Tabla1[[#This Row],[Clasificación Mercado]]="Potencial", Tabla1[[#This Row],[Margen]]>=0.3), "Media", "Baja"))) -> Alta
B31: EX027 | C31: 46255 | D31: Comercial Maya | E31: P003 | F31: Guatemala | G31: 1050 | H31: 4.8 | I31: 3.2 | J31: Embarcado | K31: =VLOOKUP(E:E,'2. Productos'!$C$3:$F$8,2,FALSE) -> Miel natural | L31: =VLOOKUP(E:E,'2. Productos'!$C$3:$E$8,3,FALSE) -> Apícola | M31: =VLOOKUP(F:F,'3. Mercados'!$C$3:$F$9,2,FALSE) -> Centroamérica | N31: =VLOOKUP(F:F,'3. Mercados'!$C$3:$F$9,3,FALSE) -> 0.03 | O31: =VLOOKUP(F:F,'3. Mercados'!$C$3:$F$9,4,FALSE) -> Estratégico | P31: =Tabla1[[#This Row],[Unidades]]*Tabla1[[#This Row],[Precio FOB]] -> 5040 | Q31: =Tabla1[[#This Row],[Unidades]]*Tabla1[[#This Row],[Costo Unitario]] -> 3360 | R31: =Tabla1[[#This Row],[Valor FOB (Free On Board)]]-Tabla1[[#This Row],[Costo total]] -> 1680 | S31: =Tabla1[[#This Row],[Utilidad]]/Tabla1[[#This Row],[Valor FOB (Free On Board)]] -> 0.33333333 | T31: =IF(Tabla1[[#This Row],[Margen]]>=30%,"Alta",IF(Tabla1[[#This Row],[Margen]]>=15%,"Media","Baja")) -> Alta | U31: =IF(Tabla1[[#This Row],[Valor FOB (Free On Board)]]>=10000,"Grande",IF(Tabla1[[#This Row],[Valor FOB (Free On Board)]]>=5000,"Mediana","Pequeña")) -> Mediana | V31: =IF(AND(Tabla1[[#This Row],[Clasificación Mercado]]="Estratégico", Tabla1[[#This Row],[Margen]]>=0.3), "Alta", IF(AND(Tabla1[[#This Row],[Clasificación Mercado]]="Estratégico", Tabla1[[#This Row],[Margen]]<0.3), "Media", IF(AND(Tabla1[[#This Row],[Clasificación Mercado]]="Potencial", Tabla1[[#This Row],[Margen]]>=0.3), "Media", "Baja"))) -> Alta
B32: EX028 | C32: 46263 | D32: Distribuidora Tica | E32: P002 | F32: Costa Rica | G32: 850 | H32: 7.1 | I32: 4.8 | J32: Entregado | K32: =VLOOKUP(E:E,'2. Productos'!$C$3:$F$8,2,FALSE) -> Cacao en grano | L32: =VLOOKUP(E:E,'2. Productos'!$C$3:$E$8,3,FALSE) -> Cacao | M32: =VLOOKUP(F:F,'3. Mercados'!$C$3:$F$9,2,FALSE) -> Centroamérica | N32: =VLOOKUP(F:F,'3. Mercados'!$C$3:$F$9,3,FALSE) -> 0.02 | O32: =VLOOKUP(F:F,'3. Mercados'!$C$3:$F$9,4,FALSE) -> Estratégico | P32: =Tabla1[[#This Row],[Unidades]]*Tabla1[[#This Row],[Precio FOB]] -> 6035 | Q32: =Tabla1[[#This Row],[Unidades]]*Tabla1[[#This Row],[Costo Unitario]] -> 4080 | R32: =Tabla1[[#This Row],[Valor FOB (Free On Board)]]-Tabla1[[#This Row],[Costo total]] -> 1955 | S32: =Tabla1[[#This Row],[Utilidad]]/Tabla1[[#This Row],[Valor FOB (Free On Board)]] -> 0.32394366 | T32: =IF(Tabla1[[#This Row],[Margen]]>=30%,"Alta",IF(Tabla1[[#This Row],[Margen]]>=15%,"Media","Baja")) -> Alta | U32: =IF(Tabla1[[#This Row],[Valor FOB (Free On Board)]]>=10000,"Grande",IF(Tabla1[[#This Row],[Valor FOB (Free On Board)]]>=5000,"Mediana","Pequeña")) -> Mediana | V32: =IF(AND(Tabla1[[#This Row],[Clasificación Mercado]]="Estratégico", Tabla1[[#This Row],[Margen]]>=0.3), "Alta", IF(AND(Tabla1[[#This Row],[Clasificación Mercado]]="Estratégico", Tabla1[[#This Row],[Margen]]<0.3), "Media", IF(AND(Tabla1[[#This Row],[Clasificación Mercado]]="Potencial", Tabla1[[#This Row],[Margen]]>=0.3), "Media", "Baja"))) -> Alta
B33: EX029 | C33: 46269 | D33: Iberia Foods | E33: P001 | F33: España | G33: 1200 | H33: 6.5 | I33: 4.1 | J33: Embarcado | K33: =VLOOKUP(E:E,'2. Productos'!$C$3:$F$8,2,FALSE) -> Café especial | L33: =VLOOKUP(E:E,'2. Productos'!$C$3:$E$8,3,FALSE) -> Café | M33: =VLOOKUP(F:F,'3. Mercados'!$C$3:$F$9,2,FALSE) -> Europa | N33: =VLOOKUP(F:F,'3. Mercados'!$C$3:$F$9,3,FALSE) -> 0.1 | O33: =VLOOKUP(F:F,'3. Mercados'!$C$3:$F$9,4,FALSE) -> Potencial | P33: =Tabla1[[#This Row],[Unidades]]*Tabla1[[#This Row],[Precio FOB]] -> 7800 | Q33: =Tabla1[[#This Row],[Unidades]]*Tabla1[[#This Row],[Costo Unitario]] -> 4920 | R33: =Tabla1[[#This Row],[Valor FOB (Free On Board)]]-Tabla1[[#This Row],[Costo total]] -> 2880 | S33: =Tabla1[[#This Row],[Utilidad]]/Tabla1[[#This Row],[Valor FOB (Free On Board)]] -> 0.36923077 | T33: =IF(Tabla1[[#This Row],[Margen]]>=30%,"Alta",IF(Tabla1[[#This Row],[Margen]]>=15%,"Media","Baja")) -> Alta | U33: =IF(Tabla1[[#This Row],[Valor FOB (Free On Board)]]>=10000,"Grande",IF(Tabla1[[#This Row],[Valor FOB (Free On Board)]]>=5000,"Mediana","Pequeña")) -> Mediana | V33: =IF(AND(Tabla1[[#This Row],[Clasificación Mercado]]="Estratégico", Tabla1[[#This Row],[Margen]]>=0.3), "Alta", IF(AND(Tabla1[[#This Row],[Clasificación Mercado]]="Estratégico", Tabla1[[#This Row],[Margen]]<0.3), "Media", IF(AND(Tabla1[[#This Row],[Clasificación Mercado]]="Potencial", Tabla1[[#This Row],[Margen]]>=0.3), "Media", "Baja"))) -> Media
B34: EX030 | C34: 46277 | D34: Comercial Azteca | E34: P004 | F34: México | G34: 600 | H34: 8.2 | I34: 5.9 | J34: Entregado | K34: =VLOOKUP(E:E,'2. Productos'!$C$3:$F$8,2,FALSE) -> Maní procesado | L34: =VLOOKUP(E:E,'2. Productos'!$C$3:$E$8,3,FALSE) -> Semillas | M34: =VLOOKUP(F:F,'3. Mercados'!$C$3:$F$9,2,FALSE) -> Norteamérica | N34: =VLOOKUP(F:F,'3. Mercados'!$C$3:$F$9,3,FALSE) -> 0.08 | O34: =VLOOKUP(F:F,'3. Mercados'!$C$3:$F$9,4,FALSE) -> Potencial | P34: =Tabla1[[#This Row],[Unidades]]*Tabla1[[#This Row],[Precio FOB]] -> 4920 | Q34: =Tabla1[[#This Row],[Unidades]]*Tabla1[[#This Row],[Costo Unitario]] -> 3540 | R34: =Tabla1[[#This Row],[Valor FOB (Free On Board)]]-Tabla1[[#This Row],[Costo total]] -> 1380 | S34: =Tabla1[[#This Row],[Utilidad]]/Tabla1[[#This Row],[Valor FOB (Free On Board)]] -> 0.2804878 | T34: =IF(Tabla1[[#This Row],[Margen]]>=30%,"Alta",IF(Tabla1[[#This Row],[Margen]]>=15%,"Media","Baja")) -> Media | U34: =IF(Tabla1[[#This Row],[Valor FOB (Free On Board)]]>=10000,"Grande",IF(Tabla1[[#This Row],[Valor FOB (Free On Board)]]>=5000,"Mediana","Pequeña")) -> Pequeña | V34: =IF(AND(Tabla1[[#This Row],[Clasificación Mercado]]="Estratégico", Tabla1[[#This Row],[Margen]]>=0.3), "Alta", IF(AND(Tabla1[[#This Row],[Clasificación Mercado]]="Estratégico", Tabla1[[#This Row],[Margen]]<0.3), "Media", IF(AND(Tabla1[[#This Row],[Clasificación Mercado]]="Potencial", Tabla1[[#This Row],[Margen]]>=0.3), "Media", "Baja"))) -> Baja
... B104: EX100 | C104: 46150 | D104: Comercial Azteca | E104: P001 | F104: México | G104: 1170 | H104: 6.5 | I104: 4.1 | J104: Entregado | K104: =VLOOKUP(E:E,'2. Productos'!$C$3:$F$8,2,FALSE) -> Café especial | L104: =VLOOKUP(E:E,'2. Productos'!$C$3:$E$8,3,FALSE) -> Café | M104: =VLOOKUP(F:F,'3. Mercados'!$C$3:$F$9,2,FALSE) -> Norteamérica | N104: =VLOOKUP(F:F,'3. Mercados'!$C$3:$F$9,3,FALSE) -> 0.08 | O104: =VLOOKUP(F:F,'3. Mercados'!$C$3:$F$9,4,FALSE) -> Potencial | P104: =Tabla1[[#This Row],[Unidades]]*Tabla1[[#This Row],[Precio FOB]] -> 7605 | Q104: =Tabla1[[#This Row],[Unidades]]*Tabla1[[#This Row],[Costo Unitario]] -> 4797 | R104: =Tabla1[[#This Row],[Valor FOB (Free On Board)]]-Tabla1[[#This Row],[Costo total]] -> 2808 | S104: =Tabla1[[#This Row],[Utilidad]]/Tabla1[[#This Row],[Valor FOB (Free On Board)]] -> 0.36923077 | T104: =IF(Tabla1[[#This Row],[Margen]]>=30%,"Alta",IF(Tabla1[[#This Row],[Margen]]>=15%,"Media","Baja")) -> Alta | U104: =IF(Tabla1[[#This Row],[Valor FOB (Free On Board)]]>=10000,"Grande",IF(Tabla1[[#This Row],[Valor FOB (Free On Board)]]>=5000,"Mediana","Pequeña")) -> Mediana | V104: =IF(AND(Tabla1[[#This Row],[Clasificación Mercado]]="Estratégico", Tabla1[[#This Row],[Margen]]>=0.3), "Alta", IF(AND(Tabla1[[#This Row],[Clasificación Mercado]]="Estratégico", Tabla1[[#This Row],[Margen]]<0.3), "Media", IF(AND(Tabla1[[#This Row],[Clasificación Mercado]]="Potencial", Tabla1[[#This Row],[Margen]]>=0.3), "Media", "Baja"))) -> Media

Sheet 2. Productos
C2: Catálogo de Productos
C3: Código | D3: Producto | E3: Categoría | F3: Unidad de Medida
C4: P001 | D4: Café especial | E4: Café | F4: Kg
C5: P002 | D5: Cacao en grano | E5: Cacao | F5: Kg
C6: P003 | D6: Miel natural | E6: Apícola | F6: Kg
C7: P004 | D7: Maní procesado | E7: Semillas | F7: Kg
C8: P005 | D8: Aceite de ajonjolí | E8: Aceites | F8: Litro

Sheet 3. Mercados
C2: Mercados
C3: País | D3: Región | E3: Arancel % | F3: Clasificación
C4: EE.UU. | D4: Norteamérica | E4: 0.05 | F4: Estratégico
C5: México | D5: Norteamérica | E5: 0.08 | F5: Potencial
C6: Guatemala | D6: Centroamérica | E6: 0.03 | F6: Estratégico
C7: Costa Rica | D7: Centroamérica | E7: 0.02 | F7: Estratégico
C8: El Salvador | D8: Centroamérica | E8: 0.02 | F8: Potencial
C9: España | D9: Europa | E9: 0.1 | F9: Potencial

Sheet 4.Analisis
A1: Analisis de informacion | D1: Valor FOB por país | G1: Ventas por región
A2: 1 ¿Cuántas operaciones internacionales se realizaron? | D2: Pais Destino | E2: Suma de Valor FOB (Free On Board) | G2: Etiquetas de fila | H2: Suma de Valor FOB (Free On Board)
A3: Se registraron un total de 100 operaciones internacionales dentro de la base de datos de exportaciones de la empresa. | D3: Costa Rica | E3: 113544 | G3: Centroamérica | H3: 232879
D4: EE.UU. | E4: 168745 | G4: Europa | H4: 136328
A5: 2 ¿Cuántas operaciones están pendientes? | D5: España | E5: 136328 | G5: Norteamérica | H5: 289058
A6: Actualmente existen 15 operaciones registradas bajo el estado de "Pendiente", las cuales requieren seguimiento logístico y comercial. | D6: Guatemala | E6: 119335 | G6: Total general | H6: 658265
D7: México | E7: 120313
A8: 3 ¿Cuál es el país con mayor cantidad de operaciones? | D8: Total general | E8: 658265
A9: El país destino con la mayor cantidad de transacciones es Guatemala, alcanzando un total de 20 operaciones.
D10: Utilidad por producto | G10: Operaciones por clasificación de prioridad
A11: 4 ¿Cuál es el país que genera mayor valor FOB? | D11: Producto | E11: Suma de Utilidad | G11: Etiquetas de fila | H11: Cuenta de ID_Operación
A12: El mercado comercial que genera el mayor ingreso en valor FOB es Estados Unidos, sumando un total de $168,745.00 USD. | D12: Aceite de ajonjolí | E12: 42218 | G12: Alta | H12: 48
D13: Cacao en grano | E13: 36800 | G13: Baja | H13: 6
A14: 5 ¿Cuál es el producto más exportado por unidades? | D14: Café especial | E14: 62832 | G14: Media | H14: 46
A15: El producto líder en volumen de exportación es el Café especial, acumulando un total de 26,180 unidades enviadas. | D15: Maní procesado | E15: 33534 | G15: Total general | H15: 100
D16: Miel natural | E16: 38688
A17: 6 ¿Cuál es el producto que genera mayor utilidad? | D17: Total general | E17: 214072
A18: El Café especial es también el producto más rentable de la empresa, aportando un total de $62,832.00 USD en utilidad.
A20: 7 ¿Cuál es el mercado con mayor margen promedio?
A21: El mercado con el mejor margen de ganancia promedio es Estados Unidos, registrante de un rendimiento promedio del 33.04%.
A23: 8 ¿Cuántas operaciones tienen rentabilidad alta?
A24: El mercado con el mejor margen de ganancia promedio es Estados Unidos, registrante de un rendimiento promedio del 33.04%.
A26: 9 ¿Cuánto se exportó hacia Centroamérica?
A27: Las exportaciones con destino a la región de Centroamérica acumularon un valor total FOB de $232,879.00 USD
A29: 10 ¿Cuánto se exportó hacia Norteamérica?
A30: El bloque comercial de Norteamérica registró el mayor volumen de ventas de la empresa, alcanzando un valor FOB de $289,058.00 USD.
A32: 11 ¿Cuánto se exportó hacia Europa?
A33: El bloque comercial de Norteamérica registró el mayor volumen de ventas de la empresa, alcanzando un valor FOB de $289,058.00 USD.
A35: 12 ¿Qué operaciones tienen prioridad comercial alta?
... A42: El cliente principal de la empresa es Global Foods, registrando la mayor concentración de compras con un valor total de $168,745.00 USD.

Sheet 5.Graficos
B25: Estados Unidos se posiciona como el mercado comercial más valioso para la empresa con un volumen total de $168,745.00 USD en exportaciones, seguido por España ($136,328.00 USD) y México ($120,313.00 USD). Costa Rica registra la menor participación monetaria con $113,544.00 USD, manteniendo una distribución relativamente equilibrada entre los cinco destinos principales. | N25: El producto estrella de la compañía es el Café Especial, generando la mayor utilidad neta con $62,832.00 USD. Le siguen el Aceite de Ajonjolí ($42,218.00 USD) y la Miel Natural ($38,688.00 USD). El Maní Procesado registra el aporte más bajo en ganancia total ($33,534.00 USD), representando una oportunidad para revisar márgenes o costos de producción.
I53: Norteamérica constituye el principal mercado regional representando el 43.9% del valor FOB total ($289,058.00 USD), seguido por Centroamérica con el 35.4% ($232,879.00 USD) y Europa con el 20.7% ($136,328.00 USD). Se evidencia una fuerte concentración del comercio en el continente americano, abarcando casi el 80% del total exportado.
